[
    { "id": 1, "word": "Elephant" },
    { "id": 2, "word": "Tiger" },
    { "id": 3, "word": "Giraffe" },
    { "id": 4, "word": "Dolphin" },
    { "id": 5, "word": "Penguin" },
    { "id": 6, "word": "Kangaroo" },
    { "id": 7, "word": "Octopus" },
    { "id": 8, "word": "Butterfly" },
    { "id": 9, "word": "Rhino" },
    { "id": 10, "word": "Koala" },
    { "id": 11, "word": "Snake" },
    { "id": 12, "word": "Lion" },
    { "id": 13, "word": "Zebra" },
    { "id": 14, "word": "Owl" },
    { "id": 15, "word": "Shark" },
    { "id": 16, "word": "Gorilla" },
    { "id": 17, "word": "Hippo" },
    { "id": 18, "word": "Fox" },
    { "id": 19, "word": "Eagle" },
    { "id": 20, "word": "Bear" },
    { "id": 21, "word": "Chair" },
    { "id": 22, "word": "Bicycle" },
    { "id": 23, "word": "Telescope" },
    { "id": 24, "word": "Guitar" },
    { "id": 25, "word": "Umbrella" },
    { "id": 26, "word": "Camera" },
    { "id": 27, "word": "Clock" },
    { "id": 28, "word": "Book" },
    { "id": 29, "word": "Computer" },
    { "id": 30, "word": "Backpack" },
    { "id": 31, "word": "Balloon" },
    { "id": 32, "word": "Lamp" },
    { "id": 33, "word": "Key" },
    { "id": 34, "word": "Glasses" },
    { "id": 35, "word": "Hammer" },
    { "id": 36, "word": "Hat" },
    { "id": 37, "word": "Rope" },
    { "id": 38, "word": "Mirror" },
    { "id": 39, "word": "Wallet" },
    { "id": 40, "word": "Basket" },
    { "id": 41, "word": "Beach" },
    { "id": 42, "word": "Forest" },
    { "id": 43, "word": "Castle" },
    { "id": 44, "word": "Hospital" },
    { "id": 45, "word": "Library" },
    { "id": 46, "word": "School" },
    { "id": 47, "word": "Park" },
    { "id": 48, "word": "Mountain" },
    { "id": 49, "word": "Desert" },
    { "id": 50, "word": "Farm" },
    { "id": 51, "word": "Airport" },
    { "id": 52, "word": "Museum" },
    { "id": 53, "word": "Restaurant" },
    { "id": 54, "word": "Stadium" },
    { "id": 55, "word": "Space" },
    { "id": 56, "word": "Jungle" },
    { "id": 57, "word": "Lake" },
    { "id": 58, "word": "Cave" },
    { "id": 59, "word": "City" },
    { "id": 60, "word": "Island" },
    { "id": 61, "word": "Running" },
    { "id": 62, "word": "Sleeping" },
    { "id": 63, "word": "Laughing" },
    { "id": 64, "word": "Swimming" },
    { "id": 65, "word": "Jumping" },
    { "id": 66, "word": "Reading" },
    { "id": 67, "word": "Dancing" },
    { "id": 68, "word": "Singing" },
    { "id": 69, "word": "Cooking" },
    { "id": 70, "word": "Drawing" },
    { "id": 71, "word": "Climbing" },
    { "id": 72, "word": "Flying" },
    { "id": 73, "word": "Eating" },
    { "id": 74, "word": "Painting" },
    { "id": 75, "word": "Writing" },
    { "id": 76, "word": "Cycling" },
    { "id": 77, "word": "Hiking" },
    { "id": 78, "word": "Driving" },
    { "id": 79, "word": "Sleeping" },
    { "id": 80, "word": "Watching" }
  ]
